parllama/__init__.py
parllama/__main__.py
parllama/app.py
parllama/app.tcss
parllama/chat_manager.py
parllama/chat_message.py
parllama/chat_message_container.py
parllama/chat_prompt.py
parllama/chat_session.py
parllama/docker_utils.py
parllama/help.md
parllama/icons.py
parllama/llm_session_helpers.py
parllama/memory_manager.py
parllama/ollama_data_manager.py
parllama/par_event_system.py
parllama/provider_manager.py
parllama/py.typed
parllama/retry_utils.py
parllama/secrets_manager.py
parllama/secure_file_ops.py
parllama/settings_manager.py
parllama/state_manager.py
parllama/theme_manager.py
parllama/update_manager.py
parllama/utils.py
parllama/dialogs/__init__.py
parllama/dialogs/edit_execution_template_dialog.py
parllama/dialogs/edit_prompt_dialog.py
parllama/dialogs/error_dialog.py
parllama/dialogs/help_dialog.py
parllama/dialogs/import_fabric_dialog.py
parllama/dialogs/import_options_dialog.py
parllama/dialogs/import_results_dialog.py
parllama/dialogs/import_templates_dialog.py
parllama/dialogs/information.py
parllama/dialogs/input_dialog.py
parllama/dialogs/model_details_dialog.py
parllama/dialogs/password_dialog.py
parllama/dialogs/text_dialog.py
parllama/dialogs/theme_dialog.py
parllama/dialogs/yes_no_dialog.py
parllama/execution/__init__.py
parllama/execution/command_executor.py
parllama/execution/execution_manager.py
parllama/execution/execution_result.py
parllama/execution/execution_template.py
parllama/execution/import_result.py
parllama/execution/template_matcher.py
parllama/messages/__init__.py
parllama/messages/messages.py
parllama/messages/par_chat_messages.py
parllama/messages/par_prompt_messages.py
parllama/messages/par_session_messages.py
parllama/messages/shared.py
parllama/models/__init__.py
parllama/models/jobs.py
parllama/models/ollama_data.py
parllama/models/ollama_ps.py
parllama/models/token_stats.py
parllama/prompt_utils/__init__.py
parllama/prompt_utils/import_fabric.py
parllama/screens/__init__.py
parllama/screens/import_session.py
parllama-0.8.3.dist-info/METADATA
parllama-0.8.3.dist-info/WHEEL
parllama-0.8.3.dist-info/entry_points.txt
parllama-0.8.3.dist-info/licenses/LICENSE
parllama-0.8.3.dist-info/RECORD
