Metadata-Version: 2.4
Name: parllama
Version: 0.8.3
Summary: Terminal UI for Ollama and other LLM providers
Project-URL: Homepage, https://github.com/paulrobello/parllama
Project-URL: Documentation, https://github.com/paulrobello/parllama/blob/main/README.md
Project-URL: Source, https://github.com/paulrobello/parllama
Project-URL: Issues, https://github.com/paulrobello/parllama/issues
Project-URL: Discussions, https://github.com/paulrobello/parllama/discussions
Project-URL: Wiki, https://github.com/paulrobello/parllama/wiki
Author-email: Paul Robello <probello@gmail.com>
Maintainer-email: Paul Robello <probello@gmail.com>
License: MIT License
License-File: LICENSE
Keywords: ai,anthropic,groq,llamacpp,llm,ollama,openai,openrouter,terminal,tui,vision,xai
Classifier: Development Status :: 4 - Beta
Classifier: Environment :: Console
Classifier: Intended Audience :: Developers
Classifier: Intended Audience :: End Users/Desktop
Classifier: Intended Audience :: Other Audience
Classifier: License :: OSI Approved :: MIT License
Classifier: Operating System :: MacOS
Classifier: Operating System :: Microsoft :: Windows :: Windows 10
Classifier: Operating System :: Microsoft :: Windows :: Windows 11
Classifier: Operating System :: POSIX :: Linux
Classifier: Programming Language :: Python :: 3
Classifier: Programming Language :: Python :: 3.11
Classifier: Programming Language :: Python :: 3.12
Classifier: Programming Language :: Python :: 3.13
Classifier: Programming Language :: Python :: 3.14
Classifier: Topic :: Scientific/Engineering :: Artificial Intelligence
Classifier: Topic :: Terminals
Classifier: Typing :: Typed
Requires-Python: >=3.11
Requires-Dist: argparse>=1.4.0
Requires-Dist: beautifulsoup4>=4.14.3
Requires-Dist: build>=1.3.0
Requires-Dist: clipman>=3.3.3
Requires-Dist: cryptography>=46.0.3
Requires-Dist: docker>=7.1.0
Requires-Dist: google-genai>=1.52.0
Requires-Dist: httpx>=0.28.1
Requires-Dist: humanize>=4.14.0
Requires-Dist: langchain>=1.1.0
Requires-Dist: ollama>=0.6.1
Requires-Dist: orjson>=3.11.4
Requires-Dist: par-ai-core>=0.5.4
Requires-Dist: pydantic-core>=2.33.1
Requires-Dist: pydantic>=2.11.3
Requires-Dist: python-dotenv>=1.2.1
Requires-Dist: pytz>=2025.2
Requires-Dist: requests>=2.32.5
Requires-Dist: rich-pixels>=3.0.1
Requires-Dist: rich>=14.2.0
Requires-Dist: semver>=3.0.4
Requires-Dist: textual-fspicker>=0.6.0
Requires-Dist: textual==6.6.0
Requires-Dist: urllib3>=2.5.0
Requires-Dist: xdg-base-dirs>=6.0.2
Provides-Extra: web
Requires-Dist: textual-serve>=1.1.2; extra == 'web'
